{
  "metadata": {
    "totalDestinations": 16,
    "successful": 0,
    "failed": 16,
    "generatedAt": "2025-07-07T11:22:28.582Z",
    "script": "Enhanced Kathmandu Destinations Enricher"
  },
  "destinations": [
    {
      "name": "Garden of Dreams",
      "categories": [
        "park",
        "garden",
        "tourist_attraction",
        "nature"
      ],
      "error": "Failed after 3 attempts.",
      "lastUpdated": "2025-07-07T11:18:26.595Z"
    },
    {
      "name": "Central Zoo, Jawalakhel",
      "categories": [
        "zoo",
        "park",
        "tourist_attraction",
        "nature",
        "entertainment"
      ],
      "error": "Failed after 3 attempts.",
      "lastUpdated": "2025-07-07T11:18:43.205Z"
    },
    {
      "name": "Phulchowki Hill",
      "categories": [
        "hill",
        "nature",
        "park",
        "hiking",
        "tourist_attraction"
      ],
      "error": "Failed after 3 attempts.",
      "lastUpdated": "2025-07-07T11:19:04.788Z"
    },
    {
      "name": "Shivapuri Nagarjun National Park",
      "categories": [
        "national_park",
        "nature",
        "forest",
        "hiking",
        "park",
        "wildlife"
      ],
      "error": "Failed after 3 attempts.",
      "lastUpdated": "2025-07-07T11:19:20.728Z"
    },
    {
      "name": "Godavari Botanical Garden",
      "categories": [
        "botanical_garden",
        "park",
        "nature",
        "garden",
        "tourist_attraction"
      ],
      "error": "Failed after 3 attempts.",
      "lastUpdated": "2025-07-07T11:19:39.378Z"
    },
    {
      "name": "Nagarkot Hill Station",
      "categories": [
        "hill",
        "nature",
        "tourist_attraction",
        "viewpoint"
      ],
      "error": "Failed after 3 attempts.",
      "lastUpdated": "2025-07-07T11:19:54.637Z"
    },
    {
      "name": "Bishnumati River Park",
      "categories": [
        "park",
        "nature",
        "river",
        "recreation"
      ],
      "error": "Failed after 3 attempts.",
      "lastUpdated": "2025-07-07T11:20:10.167Z"
    },
    {
      "name": "Dakshinkali Temple and Surrounding Forest",
      "categories": [
        "temple",
        "nature",
        "forest",
        "park",
        "religious"
      ],
      "error": "Failed after 3 attempts.",
      "lastUpdated": "2025-07-07T11:20:24.982Z"
    },
    {
      "name": "Basantapur Durbar Square Garden",
      "categories": [
        "garden",
        "historic",
        "park",
        "heritage_site"
      ],
      "error": "Failed after 3 attempts.",
      "lastUpdated": "2025-07-07T11:20:40.350Z"
    },
    {
      "name": "Rani Pokhari",
      "categories": [
        "pond",
        "historic",
        "park",
        "heritage_site",
        "tourist_attraction"
      ],
      "error": "Failed after 3 attempts.",
      "lastUpdated": "2025-07-07T11:20:55.334Z"
    },
    {
      "name": "Patan Durbar Square Gardens",
      "categories": [
        "garden",
        "historic",
        "park",
        "heritage_site"
      ],
      "error": "Failed after 3 attempts.",
      "lastUpdated": "2025-07-07T11:21:11.228Z"
    },
    {
      "name": "Nagarjun Forest Reserve",
      "categories": [
        "forest",
        "nature",
        "park",
        "wildlife"
      ],
      "error": "Failed after 3 attempts.",
      "lastUpdated": "2025-07-07T11:21:27.800Z"
    },
    {
      "name": "Balaju Water Garden",
      "categories": [
        "garden",
        "park",
        "nature",
        "water_feature"
      ],
      "error": "Failed after 3 attempts.",
      "lastUpdated": "2025-07-07T11:21:45.059Z"
    },
    {
      "name": "Tribhuvan Park",
      "categories": [
        "park",
        "recreation",
        "nature",
        "tourist_attraction"
      ],
      "error": "Failed after 3 attempts.",
      "lastUpdated": "2025-07-07T11:22:00.625Z"
    },
    {
      "name": "Pashupatinath Riverfront Park",
      "categories": [
        "park",
        "nature",
        "river",
        "religious"
      ],
      "error": "Failed after 3 attempts.",
      "lastUpdated": "2025-07-07T11:22:13.307Z"
    },
    {
      "name": "Budhanilkantha Garden Area",
      "categories": [
        "garden",
        "park",
        "nature",
        "religious"
      ],
      "error": "Failed after 3 attempts.",
      "lastUpdated": "2025-07-07T11:22:28.024Z"
    }
  ]
}